[
  {
    "metadata": {
      "title": "Web developement အကြောင်းလေ့လာခြင်း",
      "slug": "Learn",
      "locale": "my",
      "parent": {
        "slug": "Learn",
        "locale": "en-US"
      }
    },
    "probably": "en",
    "probability": 1
  },
  {
    "metadata": {
      "title": "CSS နင့် HTML အား အသွင်ပောင်းခင်း",
      "slug": "Learn/CSS",
      "locale": "my",
      "parent": {
        "slug": "Learn/CSS",
        "locale": "en-US"
      }
    },
    "probably": "en",
    "probability": 1
  },
  {
    "metadata": {
      "title": "Getting started with the Web",
      "slug": "Learn/Getting_started_with_the_web",
      "locale": "my",
      "parent": {
        "slug": "Learn/Getting_started_with_the_web",
        "locale": "en-US"
      }
    },
    "probably": "en",
    "probability": 1
  },
  {
    "metadata": {
      "title": "HTML",
      "slug": "Learn/HTML",
      "locale": "my",
      "parent": {
        "slug": "Learn/HTML",
        "locale": "en-US"
      }
    },
    "probably": "en",
    "probability": 1
  },
  {
    "metadata": {
      "title": "HTML forms",
      "slug": "Learn/HTML/Forms",
      "locale": "my",
      "parent": {
        "slug": "Learn/Forms",
        "locale": "en-US"
      }
    },
    "probably": "en",
    "probability": 1
  },
  {
    "metadata": {
      "title": "The native form widgets",
      "slug": "Learn/HTML/Forms/The_native_form_widgets",
      "locale": "my",
      "parent": {
        "slug": "Learn/Forms/Basic_native_form_controls",
        "locale": "en-US"
      }
    },
    "probably": "en",
    "probability": 1
  },
  {
    "metadata": {
      "title": "JavaScript",
      "slug": "Learn/JavaScript",
      "locale": "my",
      "parent": {
        "slug": "Learn/JavaScript",
        "locale": "en-US"
      }
    },
    "probably": "en",
    "probability": 1
  },
  {
    "metadata": {
      "title": "JavaScript First Steps",
      "slug": "Learn/JavaScript/First_steps",
      "locale": "my",
      "parent": {
        "slug": "Learn/JavaScript/First_steps",
        "locale": "en-US"
      }
    },
    "probably": "en",
    "probability": 1
  },
  {
    "metadata": {
      "title": "Arrays",
      "slug": "Learn/JavaScript/First_steps/Arrays",
      "locale": "my",
      "parent": {
        "slug": "Learn/JavaScript/First_steps/Arrays",
        "locale": "en-US"
      }
    },
    "probably": "en",
    "probability": 1
  },
  {
    "metadata": {
      "title": "အသုံးများသော string method များ",
      "slug": "Learn/JavaScript/First_steps/Useful_string_methods",
      "locale": "my",
      "parent": {
        "slug": "Learn/JavaScript/First_steps/Useful_string_methods",
        "locale": "en-US"
      }
    },
    "probably": "en",
    "probability": 1
  },
  {
    "metadata": {
      "title": "Web developers နင့္ နည္းပညာ မျာ",
      "slug": "Web",
      "locale": "my",
      "parent": {
        "slug": "Web",
        "locale": "en-US"
      }
    },
    "probably": "en",
    "probability": 1
  },
  {
    "metadata": {
      "title": "CSS: Cascading Style Sheets",
      "slug": "Web/CSS",
      "locale": "my",
      "parent": {
        "slug": "Web/CSS",
        "locale": "en-US"
      }
    },
    "probably": "en",
    "probability": 1
  },
  {
    "metadata": {
      "title": "Web developer guide",
      "slug": "Web/Guide",
      "locale": "my",
      "parent": {
        "slug": "Web/Guide",
        "locale": "en-US"
      }
    },
    "probably": "en",
    "probability": 1
  },
  {
    "metadata": {
      "title": "HTML",
      "slug": "Web/HTML",
      "locale": "my",
      "parent": {
        "slug": "Web/HTML",
        "locale": "en-US"
      }
    },
    "probably": "en",
    "probability": 1
  },
  {
    "metadata": {
      "title": "JavaScript",
      "slug": "Web/JavaScript",
      "locale": "my",
      "parent": {
        "slug": "Web/JavaScript",
        "locale": "en-US"
      }
    },
    "probably": "en",
    "probability": 1
  },
  {
    "metadata": {
      "title": "Regular Expressions",
      "slug": "Web/JavaScript/Guide/Regular_Expressions",
      "locale": "my",
      "parent": {
        "slug": "Web/JavaScript/Guide/Regular_Expressions",
        "locale": "en-US"
      }
    },
    "probably": "en",
    "probability": 1
  }
]